pychiasmodon.py
chiasmodon-3.0.3.data/scripts/chiasmodon_cli.py
chiasmodon-3.0.3.dist-info/licenses/LICENSE.txt
chiasmodon-3.0.3.dist-info/METADATA
chiasmodon-3.0.3.dist-info/WHEEL
chiasmodon-3.0.3.dist-info/top_level.txt
chiasmodon-3.0.3.dist-info/RECORD
