Metadata-Version: 2.4
Name: chiasmodon
Version: 3.0.3
Summary: Chiasmodon is an OSINT tool that allows users to gather information from various sources and conduct targeted searches based on domains, Google Play applications, email addresses, IP addresses, organizations, URLs, and more. It provides comprehensive scanning capabilities, customizable output formats, and additional options for enhanced data analysis and customization.
Home-page: https://github.com/chiasmod0n/chiasmodon
Author: chiasmod0n
Keywords: intelligence osint credentials emails asn cidr bugbounty subdomains information-gathering intelligence-analysis reconnaissance attack-surface subdomain-enumeration reconnaissance-framework bugbounty-tool email-enumeration chiasmodon
License-File: LICENSE.txt
Requires-Dist: requests
Requires-Dist: yaspin
Requires-Dist: tldextract
Requires-Dist: argcomplete
Dynamic: author
Dynamic: description
Dynamic: description-content-type
Dynamic: home-page
Dynamic: keywords
Dynamic: license-file
Dynamic: requires-dist
Dynamic: summary
